newcli/__init__.py
newcli/__version__.py
newcli/cli.py
newcli/core.py
newcli/templates/{{project}}/.editorconfig
newcli/templates/{{project}}/.gitattributes
newcli/templates/{{project}}/.gitignore
newcli/templates/{{project}}/.travis.yml
newcli/templates/{{project}}/LICENSE
newcli/templates/{{project}}/MANIFEST.in
newcli/templates/{{project}}/Pipfile
newcli/templates/{{project}}/README.md
newcli/templates/{{project}}/setup.py
newcli/templates/{{project}}/tox.ini
newcli/templates/{{project}}/{{project}}/__init__.py
newcli/templates/{{project}}/{{project}}/__version__.py
newcli/templates/{{project}}/{{project}}/cli.py
newcli/templates/{{project}}/{{project}}/core.py
newcli-2018.6.24.3.dist-info/METADATA
newcli-2018.6.24.3.dist-info/RECORD
newcli-2018.6.24.3.dist-info/WHEEL
newcli-2018.6.24.3.dist-info/entry_points.txt
newcli-2018.6.24.3.dist-info/top_level.txt
